{
  "Cooper": {
    "COOPER CLASSIC/COOPER 2DR HATCH FWD": {
      "years": [
        2002,
        2003,
        2004,
        2005,
        2006,
        2008,
        2009,
        2010,
        2011,
        2012
      ]
    },
    "COOPER S 2DR HATCH FWD": {
      "years": [
        2002,
        2003,
        2004,
        2005,
        2006,
        2007,
        2008,
        2009,
        2010,
        2011,
        2012,
        2013,
        2014
      ]
    },
    "COOPER 2DR CONVERTIBLE FWD": {
      "years": [
        2005,
        2006,
        2007,
        2008,
        2009,
        2010,
        2011,
        2012
      ]
    },
    "COOPER S 2DR CONVERTIBLE FWD": {
      "years": [
        2005,
        2006,
        2007,
        2008,
        2009,
        2010,
        2011,
        2012,
        2013,
        2014
      ]
    },
    "COOPER 2DR HATCH FWD": {
      "years": [
        2007,
        2013,
        2014
      ]
    },
    "COOPER CLUBMAN / COOPER CLUBMAN S 5DR HATCH F": {
      "years": [
        2008
      ]
    },
    "COOPER CLUBMAN 4DR HATCH FWD": {
      "years": [
        2009,
        2010,
        2011
      ]
    },
    "COOPER CLUBMAN S 4DR HATCH FWD": {
      "years": [
        2009,
        2010,
        2011
      ]
    },
    "COOPER CLUBMAN 3DR HATCH FWD": {
      "years": [
        2012,
        2013,
        2014
      ]
    },
    "COOPER CLUBMAN S 3DR HATCH FWD": {
      "years": [
        2012
      ]
    },
    "COOPER COUPE 2DR COUPE": {
      "years": [
        2012,
        2013,
        2014
      ]
    },
    "COOPER ROADSTER": {
      "years": [
        2012,
        2013,
        2014
      ]
    },
    "COOPER S COUPE 2DR COUPE": {
      "years": [
        2012,
        2013,
        2014
      ]
    },
    "COOPER S ROADSTER": {
      "years": [
        2012,
        2013,
        2014
      ]
    },
    "COOPER CLUBVAN 3DR HATCH FWD": {
      "years": [
        2013
      ]
    },
    "COOPER CONVERTIBLE 2DR FWD": {
      "years": [
        2013,
        2014
      ]
    },
    "COOPER COUNTRYMAN 4 DR SUV": {
      "years": [
        2013,
        2014
      ]
    },
    "COOPER S CLUBMAN 3DR HATCH FWD": {
      "years": [
        2013,
        2014
      ]
    },
    "COOPER S COUNTRYMAN 4 DR SUV": {
      "years": [
        2013
      ]
    },
    "COOPER S COUNTRYMAN 4 DR SUV BASE/S": {
      "years": [
        2013
      ]
    },
    "COOPER S ALL4 COUNTRYMAN 4 DR SUV AWD": {
      "years": [
        2014
      ]
    }
  },
  "Cooper S": {
    "COOPER S 2DR HATCH FWD": {
      "years": [
        2002,
        2003,
        2004,
        2005,
        2006,
        2007,
        2008,
        2009,
        2010,
        2011,
        2012,
        2013,
        2014
      ]
    },
    "COOPER S 2DR CONVERTIBLE FWD": {
      "years": [
        2005,
        2006,
        2007,
        2008,
        2009,
        2010,
        2011,
        2012,
        2013,
        2014
      ]
    },
    "COOPER S COUPE 2DR COUPE": {
      "years": [
        2012,
        2013,
        2014
      ]
    },
    "COOPER S ROADSTER": {
      "years": [
        2012,
        2013,
        2014
      ]
    },
    "COOPER S CLUBMAN 3DR HATCH FWD": {
      "years": [
        2013,
        2014
      ]
    },
    "COOPER S COUNTRYMAN 4 DR SUV": {
      "years": [
        2013
      ]
    },
    "COOPER S COUNTRYMAN 4 DR SUV BASE/S": {
      "years": [
        2013
      ]
    },
    "COOPER S ALL4 COUNTRYMAN 4 DR SUV AWD": {
      "years": [
        2014
      ]
    }
  },
  "JCW Hardtop": {},
  "Cooper Clubman": {
    "COOPER CLUBMAN / COOPER CLUBMAN S 5DR HATCH F": {
      "years": [
        2008
      ]
    },
    "COOPER CLUBMAN 4DR HATCH FWD": {
      "years": [
        2009,
        2010,
        2011
      ]
    },
    "COOPER CLUBMAN S 4DR HATCH FWD": {
      "years": [
        2009,
        2010,
        2011
      ]
    },
    "COOPER CLUBMAN 3DR HATCH FWD": {
      "years": [
        2012,
        2013,
        2014
      ]
    },
    "COOPER CLUBMAN S 3DR HATCH FWD": {
      "years": [
        2012
      ]
    }
  },
  "Cooper S Clubman": {
    "COOPER S CLUBMAN 3DR HATCH FWD": {
      "years": [
        2013,
        2014
      ]
    }
  },
  "JCW Clubman": {},
  "Cooper Convertible": {
    "COOPER CONVERTIBLE 2DR FWD": {
      "years": [
        2013,
        2014
      ]
    }
  },
  "Cooper S Convertible": {},
  "JCW Convertible": {},
  "Cooper Hardtop": {},
  "Cooper Countryman": {
    "COOPER COUNTRYMAN 4 DR SUV": {
      "years": [
        2013,
        2014
      ]
    }
  },
  "Cooper S Countryman": {
    "COOPER S COUNTRYMAN 4 DR SUV": {
      "years": [
        2013
      ]
    },
    "COOPER S COUNTRYMAN 4 DR SUV BASE/S": {
      "years": [
        2013
      ]
    }
  },
  "Cooper S Countryman All4": {},
  "Cooper S Hardtop": {},
  "Cooper Coupe": {
    "COOPER COUPE 2DR COUPE": {
      "years": [
        2012,
        2013,
        2014
      ]
    }
  },
  "Cooper S Coupe": {
    "COOPER S COUPE 2DR COUPE": {
      "years": [
        2012,
        2013,
        2014
      ]
    }
  },
  "JCW Coupe": {},
  "Cooper Roadster": {
    "COOPER ROADSTER": {
      "years": [
        2012,
        2013,
        2014
      ]
    }
  },
  "Cooper S Roadster": {
    "COOPER S ROADSTER": {
      "years": [
        2012,
        2013,
        2014
      ]
    }
  },
  "Cooper S Paceman": {},
  "Cooper Paceman": {},
  "Cooper S Paceman ALL4": {},
  "JCW Roadster": {},
  "JCW Countryman": {},
  "JCW Paceman": {},
  "Cooper S JCW GP": {}
}